imagegamepy/__init__.py
imagegamepy/game_lib.py
imagegamepy-0.0.3.dist-info/LICENSE.txt
imagegamepy-0.0.3.dist-info/METADATA
imagegamepy-0.0.3.dist-info/WHEEL
imagegamepy-0.0.3.dist-info/top_level.txt
imagegamepy-0.0.3.dist-info/RECORD
