Metadata-Version: 2.2
Name: imagegamepy
Version: 0.0.3
Summary: A package to create image games and light novels
Home-page: https://github.com/winnyblackstart/imagegamepy.git
Author: WinnyCode (Etchike Hugues Winny Lyonnais)
Author-email: <winnyblackstart@gmail.com>
License: Apache 2.0
Keywords: python,video game,Novel,game,image,image game
Classifier: Development Status :: 1 - Planning
Classifier: Intended Audience :: Developers
Classifier: Programming Language :: Python :: 3
Classifier: Operating System :: Unix
Classifier: Operating System :: MacOS :: MacOS X
Classifier: Operating System :: Microsoft :: Windows
License-File: LICENSE.txt
Requires-Dist: Pillow
Requires-Dist: pygame
Requires-Dist: numpy
Requires-Dist: keyboard
Requires-Dist: ffpyplayer
Dynamic: author
Dynamic: author-email
Dynamic: classifier
Dynamic: description
Dynamic: description-content-type
Dynamic: home-page
Dynamic: keywords
Dynamic: license
Dynamic: requires-dist
Dynamic: summary
